QSwitchControl/QSwitchControl.py
QSwitchControl/QSwitchControlplugin.py
QSwitchControl/__init__.py
QSwitchControl/__main__.py
QSwitchControl-1.0.4.dist-info/METADATA
QSwitchControl-1.0.4.dist-info/WHEEL
QSwitchControl-1.0.4.dist-info/top_level.txt
QSwitchControl-1.0.4.dist-info/RECORD
