Metadata-Version: 2.1
Name: QSwitchControl
Version: 1.0.4
Summary: An easy-to-use and modern toggle switch for Qt Python binding PyQt
Home-page: https://github.com/Prx001/QSwitchControl
Author: Parsa.py
Author-email: munichbayern2005@gmail.com
License: MIT
Platform: UNKNOWN
Classifier: License :: OSI Approved :: MIT License
Classifier: Programming Language :: Python :: 3
Classifier: Programming Language :: Python :: 3.9
Classifier: Programming Language :: Python :: Implementation :: CPython
Requires-Dist: PyQt5
